LICENSE
MANIFEST.in
README.rst
setup.cfg
setup.py
quxidget/models.py
quxidget/views.py
quxidget.egg-info/PKG-INFO
quxidget.egg-info/SOURCES.txt
quxidget.egg-info/dependency_links.txt
quxidget.egg-info/top_level.txt
quxidget/static/css/quxidget.css
quxidget/static/js/quxidget.js
quxidget/templates/feature_with_description.html
quxidget/templates/feature_with_title_only.html